repeatdecorator/README.MD
repeatdecorator/__init__.py
repeatdecorator/requirements.txt
repeatdecorator/thirdparty.json
repeatdecorator-0.10.dist-info/LICENSE.rst
repeatdecorator-0.10.dist-info/METADATA
repeatdecorator-0.10.dist-info/WHEEL
repeatdecorator-0.10.dist-info/top_level.txt
repeatdecorator-0.10.dist-info/RECORD
